{"images":[{"startdate":"20220827","fullstartdate":"202208270700","enddate":"20220828","url":"/th?id=OHR.MSHV_EN-US5482864526_UHD.jpg&rf=LaDigue_UHD.jpg&pid=hp&w=3840&h=2160&rs=1&c=4","urlbase":"/th?id=OHR.MSHV_EN-US5482864526","copyright":"Boundary Trail in Mount St. Helens National Volcanic Monument, Washington (© Don Geyer/Alamy)","copyrightlink":"/search?q=mount+st+helens+national+volcanic+monument+wiki&form=hpcapt&filters=HpDate%3a%2220220827_0700%22","title":"The recovery continues","caption":"Mount St. Helens National Volcanic Monument, Washington","copyrightonly":"© Don Geyer/Alamy","desc":"We're standing on the Boundary Trail at Johnston Ridge in the Mount St. Helens National Volcanic Monument. This view of the volcano shows how the eruption of Mount St. Helens on May 18, 1980, ripped apart the once-conical summit, forever changing the Washington landscape. Forty years ago today, 110,000 acres within Gifford Pinchot National Forest were set aside to memorialize the deadliest and most destructive volcanic eruption in the United States.","date":"Aug 27, 2022","bsTitle":"The recovery continues","quiz":"/search?q=Bing+homepage+quiz&filters=WQOskey:%22HPQuiz_20220827_MSHV%22&FORM=HPQUIZ","wp":true,"hsh":"07a28a6c5dd057b65376e6c0c1da5a67","drk":1,"top":1,"bot":1,"hs":[]}],"tooltips":{"loading":"Loading...","previous":"Previous image","next":"Next image","walle":"This image is not available to download as wallpaper.","walls":"Download this image. Use of this image is restricted to wallpaper only."}}