{"images":[{"startdate":"20230709","fullstartdate":"202307090700","enddate":"20230710","url":"/th?id=OHR.MoselleRiver_EN-US2499319157_UHD.jpg&rf=LaDigue_UHD.jpg&pid=hp&w=3840&h=2160&rs=1&c=4","urlbase":"/th?id=OHR.MoselleRiver_EN-US2499319157","copyright":"Moselle River loop, Kröv, Germany (© Jorg Greuel/Getty Images)","copyrightlink":"/search?q=Moselle+River&form=hpcapt&filters=HpDate%3a%2220230709_0700%22","title":"In the loop","caption":"Moselle River loop near Kröv, Germany","copyrightonly":"© Jorg Greuel/Getty Images","desc":"The Moselle River, a tributary of the powerful Rhine, meanders through the landscapes of France, Luxembourg, and Germany. Along the way, it carves out valleys of breathtaking natural beauty, dotted with towns and historic landmarks. Lush, sun-drenched vineyards cling to the steep slopes overlooking the river, producing some of the finest wines in the world, including riesling, pinot blanc, and pinot gris, to name a few. The river's gentle flow and sparkling waters invite visitors to embark on leisurely cruises or peaceful walks along its shores. The Moselle creates a haven for nature lovers, wine enthusiasts, and history buffs alike.","date":"Jul 9, 2023","bsTitle":"In the loop","quiz":"/search?q=Bing+homepage+quiz&filters=WQOskey:%22HPQuiz_20230709_MoselleRiver%22&FORM=HPQUIZ","wp":true,"hsh":"52fcc801c31d6fc9194dd620a8de640d","drk":1,"top":1,"bot":1,"hs":[]}],"tooltips":{"loading":"Loading...","previous":"Previous image","next":"Next image","walle":"This image is not available to download as wallpaper.","walls":"Download this image. Use of this image is restricted to wallpaper only."}}