{"images":[{"startdate":"20241224","fullstartdate":"202412240800","enddate":"20241225","url":"/th?id=OHR.SantaSnowglobe_EN-US0704281966_UHD.jpg&rf=LaDigue_UHD.jpg&pid=hp&w=3840&h=2160&rs=1&c=4","urlbase":"/th?id=OHR.SantaSnowglobe_EN-US0704281966","copyright":"Christmas market scene in Germany (© Cyril Gosselin/Getty Images)","copyrightlink":"/search?q=Christmas+Eve&form=hpcapt&filters=HpDate%3a%2220241224_0800%22","title":"Have yourself a very merry Christmas!","caption":"Silent night, sparkling lights, and hearts full of joy","copyrightonly":"© Cyril Gosselin/Getty Images","desc":"Christmas markets in Germany are a cherished holiday tradition that welcome visitors into a magical world of twinkling lights, festive music, and delicious seasonal treats. These markets date back to the Middle Ages and are held in town squares throughout Germany, with iconic examples in cities such as Nuremberg, Munich, and Dresden. Each market displays unique regional crafts and festive customs. Here, guests can discover handcrafted ornaments, wooden toys, and cozy winter accessories, along with specialties like Glühwein (mulled wine), Lebkuchen (gingerbread), and roasted nuts—ideal for enjoying while immersing themselves in the enchanting atmosphere.","date":"Dec 24, 2024","bsTitle":"Have yourself a very merry Christmas!","quiz":"/search?q=Bing+homepage+quiz&filters=WQOskey:%22HPQuiz_20241224_SantaSnowglobe%22&FORM=HPQUIZ","wp":true,"hsh":"1f1c4293d0cae09c9e698bdd07edffd5","drk":1,"top":1,"bot":1,"hs":[]}],"tooltips":{"loading":"Loading...","previous":"Previous image","next":"Next image","walle":"This image is not available to download as wallpaper.","walls":"Download this image. Use of this image is restricted to wallpaper only."}}