{"images":[{"startdate":"20250331","fullstartdate":"202503310700","enddate":"20250401","url":"/th?id=OHR.ItalyOstuni_EN-US2964422003_UHD.jpg&rf=LaDigue_UHD.jpg&pid=hp&w=3840&h=2160&rs=1&c=4","urlbase":"/th?id=OHR.ItalyOstuni_EN-US2964422003","copyright":"Ostuni at dusk, Apulia, Italy (© Feng Wei Photography/Getty Images)","copyrightlink":"/search?q=Ostuni+Italy&form=hpcapt&filters=HpDate%3a%2220250331_0700%22","title":"Apulia's White City","caption":"Ostuni, Apulia, Italy","copyrightonly":"© Feng Wei Photography/Getty Images","desc":"Perched on a hilltop overlooking the Adriatic Sea, there is a historic city that enchants visitors with its labyrinth of whitewashed buildings, winding alleyways, and a sun-drenched piazza. Welcome to Ostuni, in the Apulia region of Italy. Apulia is a southeastern area of the country, located in the heel of Italy's 'boot.' It has the longest coastline of any mainland region in the country and is home to numerous attractions, including beaches, cliffs, and charming cities like the one we see in today's image.","date":"Mar 31, 2025","bsTitle":"Apulia's White City","quiz":"/search?q=Bing+homepage+quiz&filters=WQOskey:%22HPQuiz_20250331_ItalyOstuni%22&FORM=HPQUIZ","wp":true,"hsh":"227e9b248b999178eaf569282c0d6257","drk":1,"top":1,"bot":1,"hs":[]}],"tooltips":{"loading":"Loading...","previous":"Previous image","next":"Next image","walle":"This image is not available to download as wallpaper.","walls":"Download this image. Use of this image is restricted to wallpaper only."}}