{"images":[{"startdate":"20260218","fullstartdate":"202602180800","enddate":"20260219","url":"/th?id=OHR.PrzewalskisHorse_EN-US6767229079_UHD.jpg&rf=LaDigue_UHD.jpg&pid=hp&w=3840&h=2160&rs=1&c=4","urlbase":"/th?id=OHR.PrzewalskisHorse_EN-US6767229079","copyright":"Przewalski's horses (© Nemyrivskyi Viacheslav/Getty Images)","copyrightlink":"/search?q=Przewalskis+horse&form=hpcapt&filters=HpDate%3a%2220260218_0800%22","title":"Born to stay wild","caption":"Przewalski's horses","copyrightonly":"© Nemyrivskyi Viacheslav/Getty Images","desc":"This species missed the domestication memo and kept going on its own terms. Say hello to Przewalski's horse, considered the last truly wild horse on Earth. Once widespread across Central Asia, it disappeared from the wild in the 1960s after decades of hunting, habitat loss, and competition with livestock. Its survival depended on an unlikely lifeline: a small number of individuals captured by early 20th‑century collectors, which became the foundation of all modern Przewalski's horses.","date":"Feb 18, 2026","bsTitle":"Born to stay wild","quiz":"/search?q=Bing+homepage+quiz&filters=WQOskey:%22HPQuiz_20260218_PrzewalskisHorse%22&FORM=HPQUIZ","wp":true,"hsh":"47aa8f61af1dda63aff0c1d502511ff7","drk":1,"top":1,"bot":1,"hs":[]}],"tooltips":{"loading":"Loading...","previous":"Previous image","next":"Next image","walle":"This image is not available to download as wallpaper.","walls":"Download this image. Use of this image is restricted to wallpaper only."}}