{"images":[{"startdate":"20260401","fullstartdate":"202604010700","enddate":"20260402","url":"/th?id=OHR.JapaneseTreeFrog_EN-US6527297660_UHD.jpg&rf=LaDigue_UHD.jpg&pid=hp&w=3840&h=2160&rs=1&c=4","urlbase":"/th?id=OHR.JapaneseTreeFrog_EN-US6527297660","copyright":"Japanese tree frog in a pink morning glory (© Tetsuya Tanooka/Getty Images)","copyrightlink":"/search?q=National+Frog+Month&form=hpcapt&filters=HpDate%3a%2220260401_0700%22","title":"Hopping into April","caption":"National Frog Month","copyrightonly":"© Tetsuya Tanooka/Getty Images","desc":"April is National Frog Month, a time to appreciate one of nature's smallest yet most remarkable ambassadors. Frogs help balance insect populations and often serve as early indicators of environmental change, as their permeable skin readily responds to shifts in water and air quality. Their presence reveals much about the health of their habitats, making this month a fitting time to pause and recognize their vital role.","date":"Apr 1, 2026","bsTitle":"Hopping into April","quiz":"/search?q=Bing+homepage+quiz&filters=WQOskey:%22HPQuiz_20260401_JapaneseTreeFrog%22&FORM=HPQUIZ","wp":true,"hsh":"23d14cf9501ce40edca20437f5f98e4b","drk":1,"top":1,"bot":1,"hs":[]}],"tooltips":{"loading":"Loading...","previous":"Previous image","next":"Next image","walle":"This image is not available to download as wallpaper.","walls":"Download this image. Use of this image is restricted to wallpaper only."}}